pyipcore/__init__.py
pyipcore/icon_rc.py
pyipcore/ip_module_view.py
pyipcore/ipc_utils.py
pyipcore/ipcdir.py
pyipcore/ipcore.py
pyipcore/ipcore_support_functions.py
pyipcore/ipcrc.py
pyipcore/main.py
pyipcore/parsetab.py
pyipcore/splash.py
pyipcore/test.py
pyipcore/test2.py
pyipcore/tfi.py
pyipcore/ui_utils.py
pyipcore/utils.py
pyipcore/ui_main/__init__.py
pyipcore/ui_main/ui_main.py
pyipcore/ui_main/ui_style.py
pyipcore/ui_main/creator_page/__init__.py
pyipcore/ui_main/creator_page/ipc_creator.py
pyipcore/ui_main/tablexp_page/__init__.py
pyipcore/ui_main/tablexp_page/_tools.py
pyipcore-0.4.34.dist-info/METADATA
pyipcore-0.4.34.dist-info/WHEEL
pyipcore-0.4.34.dist-info/entry_points.txt
pyipcore-0.4.34.dist-info/top_level.txt
pyipcore-0.4.34.dist-info/RECORD
