Metadata-Version: 2.1
Name: pyipcore
Version: 0.4.34
Summary: (PyQt5 based) Create "Ipcore" from verilog(Need iverilog). Provide "Param Value" and "Port Control" function. This kind of IpCore is not safe, only for convenience
Author-email: 2229066748@qq.com
Maintainer: Eagle'sBaby
Maintainer-email: 2229066748@qq.com
License: Apache Licence 2.0
Keywords: verilog,ipcore,pyqt5
Classifier: Programming Language :: Python :: 3
Classifier: Operating System :: Microsoft :: Windows
Requires-Python: >=3.10
Requires-Dist: PyQt5>=5.15
Requires-Dist: QScintilla
Requires-Dist: PyQtWebEngine>=5.15
Requires-Dist: reft>=0.3.5
Requires-Dist: markdown>=3.5.2
Requires-Dist: pyverilog==1.3.0
Requires-Dist: rbpop>=0.1.4
Requires-Dist: files3>=0.9.1
Requires-Dist: chardet
Requires-Dist: pandas
Requires-Dist: qwork>=0.0.4
